pyzipper/__init__.py
pyzipper/__version__.py
pyzipper/zipfile.py
pyzipper/zipfile_aes.py
test/support/__init__.py
test/support/script_helper.py
test/support/testresult.py
pyzipper-0.3.6.dist-info/AUTHORS.rst
pyzipper-0.3.6.dist-info/LICENSE
pyzipper-0.3.6.dist-info/LICENSE~
pyzipper-0.3.6.dist-info/METADATA
pyzipper-0.3.6.dist-info/WHEEL
pyzipper-0.3.6.dist-info/top_level.txt
pyzipper-0.3.6.dist-info/RECORD
